neuroplay_alt_sdk/__init__.py
neuroplay_alt_sdk/native/__init__.py
neuroplay_alt_sdk/native/csv/__init__.py
neuroplay_alt_sdk/native/csv/abstract_csv_writer.py
neuroplay_alt_sdk/native/csv/csv_annotations_writer.py
neuroplay_alt_sdk/native/csv/csv_data_writer.py
neuroplay_alt_sdk/native/csv/csv_util.py
neuroplay_alt_sdk/native/devices/__init__.py
neuroplay_alt_sdk/native/devices/abstract_neuroplay_device.py
neuroplay_alt_sdk/native/devices/neuroplay_device.py
neuroplay_alt_sdk/native/edf/__init__.py
neuroplay_alt_sdk/native/edf/edf_creator.py
neuroplay_alt_sdk/native/enums/__init__.py
neuroplay_alt_sdk/native/enums/data_status_enum.py
neuroplay_alt_sdk/native/enums/neuroplay_devices_enum.py
neuroplay_alt_sdk/native/exceptions/__init__.py
neuroplay_alt_sdk/native/exceptions/neuroplay_exceptions.py
neuroplay_alt_sdk/native/filters/__init__.py
neuroplay_alt_sdk/native/filters/abstract_filter.py
neuroplay_alt_sdk/native/filters/continuous_filter.py
neuroplay_alt_sdk/native/filters/continuous_notch_filter.py
neuroplay_alt_sdk/native/filters/filters_container.py
neuroplay_alt_sdk/native/scanner/__init__.py
neuroplay_alt_sdk/native/scanner/neuroplay_scanner.py
neuroplay_alt_sdk/native/utils/__init__.py
neuroplay_alt_sdk/native/utils/data_synchronizer.py
neuroplay_alt_sdk-1.1.2.dist-info/METADATA
neuroplay_alt_sdk-1.1.2.dist-info/WHEEL
neuroplay_alt_sdk-1.1.2.dist-info/RECORD
