Metadata-Version: 2.3
Name: neuroplay-alt-sdk
Version: 1.1.2
Summary: An asynchronous Python library for working with NeuroPlay EEG devices.
Author: v14d4n
Requires-Python: >=3.12,<3.13
Classifier: Programming Language :: Python :: 3
Classifier: Programming Language :: Python :: 3.12
Requires-Dist: bleak (>=0.22.2,<0.23.0)
Requires-Dist: numpy (>=2.1.1,<3.0.0)
Requires-Dist: pandas (>=2.2.3,<3.0.0)
Requires-Dist: pyedflib (>=0.1.38,<0.2.0)
Requires-Dist: scipy (>=1.14.1,<2.0.0)
